odoo/addons/rental_timeline/README.rst
odoo/addons/rental_timeline/__init__.py
odoo/addons/rental_timeline/__manifest__.py
odoo/addons/rental_timeline/README/CONTRIBUTORS.rst
odoo/addons/rental_timeline/README/DESCRIPTION.rst
odoo/addons/rental_timeline/README/HISTORY.rst
odoo/addons/rental_timeline/README/USAGE.rst
odoo/addons/rental_timeline/i18n/de.po
odoo/addons/rental_timeline/i18n/rental_timeline.pot
odoo/addons/rental_timeline/models/__init__.py
odoo/addons/rental_timeline/models/ir_actions.py
odoo/addons/rental_timeline/models/ir_view.py
odoo/addons/rental_timeline/models/product.py
odoo/addons/rental_timeline/models/product_timeline.py
odoo/addons/rental_timeline/models/res_partner.py
odoo/addons/rental_timeline/models/sale.py
odoo/addons/rental_timeline/security/ir.model.access.csv
odoo/addons/rental_timeline/static/description/icon.png
odoo/addons/rental_timeline/static/description/index.html
odoo/addons/rental_timeline/static/src/js/Popup.js
odoo/addons/rental_timeline/static/src/js/timeline_controller.js
odoo/addons/rental_timeline/static/src/js/timeline_renderer.js
odoo/addons/rental_timeline/static/src/js/timeline_view.js
odoo/addons/rental_timeline/static/src/scss/rental_timeline.scss
odoo/addons/rental_timeline/tests/__init__.py
odoo/addons/rental_timeline/tests/test_rental_timeline.py
odoo/addons/rental_timeline/views/assets.xml
odoo/addons/rental_timeline/views/product_timeline_view.xml
odoo/addons/rental_timeline/views/product_view.xml
odoo12_addon_rental_timeline-12.0.1.0.0.99.dev2.dist-info/METADATA
odoo12_addon_rental_timeline-12.0.1.0.0.99.dev2.dist-info/WHEEL
odoo12_addon_rental_timeline-12.0.1.0.0.99.dev2.dist-info/top_level.txt
odoo12_addon_rental_timeline-12.0.1.0.0.99.dev2.dist-info/RECORD
