Metadata-Version: 2.1
Name: odoo12-addon-rental-timeline
Version: 12.0.1.0.0.99.dev2
Summary: Timeline view for rental orders and rental products
Home-page: https://github.com/OCA/vertical-rental
Author: elego Software Solutions GmbH, Odoo Community Association (OCA)
Author-email: support@odoo-community.org
License: AGPL-3
Platform: UNKNOWN
Classifier: Programming Language :: Python
Classifier: Framework :: Odoo
Classifier: Framework :: Odoo :: 12.0
Classifier: License :: OSI Approved :: GNU Affero General Public License v3
Requires-Python: >=3.5
Requires-Dist: odoo12-addon-rental-base
Requires-Dist: odoo12-addon-web-timeline
Requires-Dist: odoo <12.1dev,>=12.0a
